admonitions/__init__.py
admonitions/admonition.py
mkdocs_github_admonitions_plugin-0.1.1.dist-info/METADATA
mkdocs_github_admonitions_plugin-0.1.1.dist-info/WHEEL
mkdocs_github_admonitions_plugin-0.1.1.dist-info/entry_points.txt
mkdocs_github_admonitions_plugin-0.1.1.dist-info/licenses/LICENSE
mkdocs_github_admonitions_plugin-0.1.1.dist-info/RECORD
