Metadata-Version: 2.4
Name: mkdocs-github-admonitions-plugin
Version: 0.1.1
Summary: Convert GitHub admonitions to mkdocs syntax when building docs.
Project-URL: Homepage, https://pgijsbers.github.io/admonitions
Project-URL: Repository, https://www.github.com/pgijsbers/admonitions.git
Project-URL: Issues, https://www.github.com/pgijsbers/admonitions/issues
Author: Pieter Gijsbers
License-File: LICENSE
Keywords: admonition,github,material,mkdocs
Classifier: Development Status :: 4 - Beta
Classifier: Framework :: MkDocs
Classifier: Intended Audience :: Developers
Classifier: License :: OSI Approved :: MIT License
Classifier: Natural Language :: English
Classifier: Programming Language :: Python :: 3
Classifier: Topic :: Documentation
Requires-Python: >=3.8
Requires-Dist: mkdocs
Provides-Extra: dev
Requires-Dist: pytest; extra == 'dev'
Provides-Extra: docs
Requires-Dist: mkdocs-material; extra == 'docs'
